Metadata-Version: 2.1
Name: pystencils-autodiff
Version: 0.3.3
Summary: Automatic differentiation and generation of Torch/Tensorflow operations with pystencils (https://i10git.cs.fau.de/pycodegen/pystencils)
Home-page: https://github.com/theHamsta/pystencils_autodiff
Author: Stephan Seitz
Author-email: stephan.seitz@fau.de
License: GPLv3
Project-URL: Documentation, https://pystencils-autodiff.readthedocs.io/en/latest/
Platform: any
Classifier: Development Status :: 4 - Beta
Classifier: Programming Language :: Python
Provides-Extra: pybind11
Provides-Extra: testing
